{"_type":"export","__export_format":4,"__export_date":"2023-10-17T02:31:52.772Z","__export_source":"insomnia.desktop.app:v2023.5.8","resources":[{"_id":"req_f517ff09533b425eaf6664af166fa1ad","parentId":"fld_29fba9fc0cbf452dae4f85f4c38c9305","modified":1697508072010,"created":1694316309714,"url":"{{ _.baseUrl }}/v1/wallet/balance-account","name":"Balance","description":"","method":"GET","body":{"mimeType":"application/json","text":""},"parameters":[],"headers":[{"name":"Content-Type","value":"application/json"},{"name":"User-Agent","value":"Insomnia/2023.5.7"}],"authentication":{"type":"bearer","token":"{% response 'body', 'req_96b7e6a46bd249dc8ed8be708b9c5501', 'b64::JC50b2tlbg==::46b', 'never', 60 %}"},"metaSortKey":-1694316309714,"isPrivate":false,"settingStoreCookies":true,"settingSendCookies":true,"settingDisableRenderRequestBody":false,"settingEncodeUrl":true,"settingRebuildPath":true,"settingFollowRedirects":"global","_type":"request"},{"_id":"fld_29fba9fc0cbf452dae4f85f4c38c9305","parentId":"wrk_2c9df4d661dc424f8fb66d6f9cb4a7c1","modified":1694316252248,"created":1694316252248,"name":"Wallet","description":"","environment":{},"environmentPropertyOrder":null,"metaSortKey":-1694316252248,"_type":"request_group"},{"_id":"wrk_2c9df4d661dc424f8fb66d6f9cb4a7c1","parentId":null,"modified":1689213535253,"created":1689213535253,"name":"NaRegua.API","description":"","scope":"collection","_type":"workspace"},{"_id":"req_197cb10f9b9742e288742b3366af4c75","parentId":"fld_29fba9fc0cbf452dae4f85f4c38c9305","modified":1697509749809,"created":1694316258251,"url":"{{ _.baseUrl }}/v1/wallet/add-funds","name":"add-funds","description":"","method":"POST","body":{"mimeType":"application/json","text":"{\n\t\"Value\": 200,\n\t\"PaymentType\": 1,\n\t\"CardNumber\": \"204510\"\n}"},"parameters":[],"headers":[{"name":"Content-Type","value":"application/json"},{"name":"User-Agent","value":"Insomnia/2023.5.7"}],"authentication":{"type":"bearer","token":"{% response 'body', 'req_96b7e6a46bd249dc8ed8be708b9c5501', 'b64::JC50b2tlbg==::46b', 'never', 60 %}"},"metaSortKey":-1694316258251,"isPrivate":false,"settingStoreCookies":true,"settingSendCookies":true,"settingDisableRenderRequestBody":false,"settingEncodeUrl":true,"settingRebuildPath":true,"settingFollowRedirects":"global","_type":"request"},{"_id":"req_22dfd10098674f1d96c25957a5c59e5a","parentId":"fld_969265b72812455ab2606a6d16833856","modified":1697508017715,"created":1689214157464,"url":"{{ _.baseUrl }}/v1/publickey","name":"Get Public Key","description":"","method":"GET","body":{},"parameters":[],"headers":[{"id":"pair_c9864e8068b1423dad19343cbfac2886","name":"X-Encryption","value":"","description":""},{"id":"pair_ca6f9fe02e8447ee8c78c61023064704","name":"","value":"","description":""}],"authentication":{},"metaSortKey":-1689214157464,"isPrivate":false,"settingStoreCookies":true,"settingSendCookies":true,"settingDisableRenderRequestBody":false,"settingEncodeUrl":true,"settingRebuildPath":true,"settingFollowRedirects":"global","_type":"request"},{"_id":"fld_969265b72812455ab2606a6d16833856","parentId":"wrk_2c9df4d661dc424f8fb66d6f9cb4a7c1","modified":1689214121619,"created":1689214121619,"name":"Criptograph","description":"","environment":{},"environmentPropertyOrder":null,"metaSortKey":-1689214121619,"_type":"request_group"},{"_id":"req_e1eb5c3f1d4c40129a40c502603842de","parentId":"fld_969265b72812455ab2606a6d16833856","modified":1689214519659,"created":1689214482673,"url":"https://localhost:3000/v1/publickey","name":"Post Data Encrypt","description":"","method":"POST","body":{"mimeType":"application/json","text":"{\n\t\"Teste\":\"dasdsa\"\n}"},"parameters":[],"headers":[{"name":"Content-Type","value":"application/json"}],"authentication":{},"metaSortKey":-1675085771871,"isPrivate":false,"settingStoreCookies":true,"settingSendCookies":true,"settingDisableRenderRequestBody":false,"settingEncodeUrl":true,"settingRebuildPath":true,"settingFollowRedirects":"global","_type":"request"},{"_id":"req_96b7e6a46bd249dc8ed8be708b9c5501","parentId":"fld_587aa00ed9134adab7321bcfd373e56f","modified":1697509740734,"created":1657894294304,"url":"{{ _.baseUrl }}/v1/auth/sign","name":"Sign","description":"","method":"POST","body":{"mimeType":"application/json","text":"{\n\t\"username\": \"leskfp\",\n\t\"password\": \"123456\"\n}"},"parameters":[],"headers":[{"name":"Content-Type","value":"application/json","id":"pair_2af82f2d87c6464fab5ac1a570b26f15"}],"authentication":{"type":"bearer","token":""},"metaSortKey":-1657894294304,"isPrivate":false,"settingStoreCookies":true,"settingSendCookies":true,"settingDisableRenderRequestBody":false,"settingEncodeUrl":true,"settingRebuildPath":true,"settingFollowRedirects":"global","_type":"request"},{"_id":"fld_587aa00ed9134adab7321bcfd373e56f","parentId":"wrk_2c9df4d661dc424f8fb66d6f9cb4a7c1","modified":1659974634284,"created":1659974634284,"name":"Auth","description":"","environment":{},"environmentPropertyOrder":null,"metaSortKey":-1659974634284,"_type":"request_group"},{"_id":"req_5201af5f14104324947024d73e0ae4fb","parentId":"fld_878f2c41dcda401eaad61b767ca233a4","modified":1697507266557,"created":1697344407244,"url":"https://localhost:3000/v1/user/favorite-salon/045B79","name":"Delete favorite saloon","description":"","method":"DELETE","body":{},"parameters":[],"headers":[{"name":"User-Agent","value":"insomnia/2023.5.8"}],"authentication":{"type":"bearer","token":"{% response 'body', 'req_96b7e6a46bd249dc8ed8be708b9c5501', 'b64::JC50b2tlbg==::46b', 'never', 60 %}"},"metaSortKey":-1697344407244,"isPrivate":false,"settingStoreCookies":true,"settingSendCookies":true,"settingDisableRenderRequestBody":false,"settingEncodeUrl":true,"settingRebuildPath":true,"settingFollowRedirects":"global","_type":"request"},{"_id":"fld_878f2c41dcda401eaad61b767ca233a4","parentId":"wrk_2c9df4d661dc424f8fb66d6f9cb4a7c1","modified":1659974628332,"created":1659974628332,"name":"Users","description":"","environment":{},"environmentPropertyOrder":null,"metaSortKey":-1659974628332,"_type":"request_group"},{"_id":"req_38dc123abf7842ae9b6036fbd89ca4cc","parentId":"fld_878f2c41dcda401eaad61b767ca233a4","modified":1697344335637,"created":1697344241925,"url":"https://localhost:3000/v1/user/favorite-salon","name":"Get Favorites Saloons","description":"","method":"GET","body":{},"parameters":[],"headers":[{"name":"User-Agent","value":"insomnia/2023.5.8"}],"authentication":{"type":"bearer","token":"{% response 'body', 'req_96b7e6a46bd249dc8ed8be708b9c5501', 'b64::JC50b2tlbg==::46b', 'never', 60 %}"},"metaSortKey":-1697344241925,"isPrivate":false,"settingStoreCookies":true,"settingSendCookies":true,"settingDisableRenderRequestBody":false,"settingEncodeUrl":true,"settingRebuildPath":true,"settingFollowRedirects":"global","_type":"request"},{"_id":"req_5ff965f95eb04d1ca4ecf442f1b7a7b9","parentId":"fld_878f2c41dcda401eaad61b767ca233a4","modified":1697344398293,"created":1660957386278,"url":"https://localhost:3000/v1/user/favorite-salon","name":"Post Salon As Favorite","description":"","method":"POST","body":{"mimeType":"application/json","text":"{\n\t\"saloonCode\":\"045B79\"\n}"},"parameters":[],"headers":[{"name":"Content-Type","value":"application/json","id":"pair_c057f19266104eea98effb74cbf8d294"}],"authentication":{"type":"bearer","token":"{% response 'body', 'req_96b7e6a46bd249dc8ed8be708b9c5501', 'b64::JC50b2tlbg==::46b', 'never', 60 %}"},"metaSortKey":-1660957386278,"isPrivate":false,"settingStoreCookies":true,"settingSendCookies":true,"settingDisableRenderRequestBody":false,"settingEncodeUrl":true,"settingRebuildPath":true,"settingFollowRedirects":"global","_type":"request"},{"_id":"req_5916f7ef3b7547d583bac84367f23f0d","parentId":"fld_878f2c41dcda401eaad61b767ca233a4","modified":1692457258253,"created":1660957158025,"url":"https://localhost:3000/v1/user/schedule-appointment","name":"Schedule Appointment","description":"","method":"GET","body":{},"parameters":[],"headers":[],"authentication":{"type":"bearer","token":"{% response 'body', 'req_96b7e6a46bd249dc8ed8be708b9c5501', 'b64::JC50b2tlbg==::46b', 'never', 60 %}"},"metaSortKey":-1660957158025,"isPrivate":false,"settingStoreCookies":true,"settingSendCookies":true,"settingDisableRenderRequestBody":false,"settingEncodeUrl":true,"settingRebuildPath":true,"settingFollowRedirects":"global","_type":"request"},{"_id":"req_119d6465a1d948fa9b24d21bbfb4a48b","parentId":"fld_878f2c41dcda401eaad61b767ca233a4","modified":1697349879062,"created":1660009462504,"url":"https://localhost:3000/v1/user/schedule-appointment","name":"Schedule Appointment","description":"","method":"POST","body":{"mimeType":"application/json","text":"{\n\t\"documentProfessional\": \"48280663061\",\n\t\"dateTime\": \"2023-10-16T08:00:00\"\n}"},"parameters":[],"headers":[{"name":"Content-Type","value":"application/json","id":"pair_07ec9fb644b745b38967c6a4d5ea2bbe"}],"authentication":{"type":"bearer","token":"{% response 'body', 'req_96b7e6a46bd249dc8ed8be708b9c5501', 'b64::JC50b2tlbg==::46b', 'never', 60 %}"},"metaSortKey":-1657894149753,"isPrivate":false,"settingStoreCookies":true,"settingSendCookies":true,"settingDisableRenderRequestBody":false,"settingEncodeUrl":true,"settingRebuildPath":true,"settingFollowRedirects":"global","_type":"request"},{"_id":"req_d8bddf0671fe41f5a26512debe829ad6","parentId":"fld_878f2c41dcda401eaad61b767ca233a4","modified":1697508052430,"created":1657894149703,"url":"{{ _.baseUrl }}/v1/user","name":"Create User","description":"","method":"POST","body":{"mimeType":"application/json","text":"{\n\t\"name\": \"Alex\",\n\t\"Document\": \"14120252736\",\n\t\"email\": \"alexcachopa@hotmail.com\",\n\t\"phone\": \"21979522952\",\n\t\"username\": \"leskfp\",\n\t\"password\": \"123456\"\n}"},"parameters":[],"headers":[{"name":"Content-Type","value":"application/json","id":"pair_4bc0aabfc9eb4357a284d1c00f94e9eb"}],"authentication":{},"metaSortKey":-1657894149703,"isPrivate":false,"settingStoreCookies":true,"settingSendCookies":true,"settingDisableRenderRequestBody":false,"settingEncodeUrl":true,"settingRebuildPath":true,"settingFollowRedirects":"global","_type":"request"},{"_id":"req_87635dbac50742d6a2cbd3fbe18cc9ad","parentId":"fld_e2a5fb58c8644010b6b1d81383473705","modified":1697349902177,"created":1660956752628,"url":"https://localhost:3000/v1/hairdresser/evaluation-average","name":"Send Evaluation Average","description":"","method":"POST","body":{"mimeType":"application/json","text":"{\n\t\"document\": \"48280663061\",\n  \"evaluation\": 4\n}"},"parameters":[],"headers":[{"name":"Content-Type","value":"application/json","id":"pair_1c83daeec9874d73b559072018126032"}],"authentication":{"type":"bearer","token":"{% response 'body', 'req_96b7e6a46bd249dc8ed8be708b9c5501', 'b64::JC50b2tlbg==::46b', 'never', 60 %}"},"metaSortKey":-1660956752628,"isPrivate":false,"settingStoreCookies":true,"settingSendCookies":true,"settingDisableRenderRequestBody":false,"settingEncodeUrl":true,"settingRebuildPath":true,"settingFollowRedirects":"global","_type":"request"},{"_id":"fld_e2a5fb58c8644010b6b1d81383473705","parentId":"wrk_2c9df4d661dc424f8fb66d6f9cb4a7c1","modified":1659974619164,"created":1659974619164,"name":"Hairdressers","description":"","environment":{},"environmentPropertyOrder":null,"metaSortKey":-1659974619164,"_type":"request_group"},{"_id":"req_7d560a532b4c4a80b31677df9c7f436e","parentId":"fld_e2a5fb58c8644010b6b1d81383473705","modified":1697345083745,"created":1660956656573,"url":"https://localhost:3000/v1/hairdresser/evaluation-average/48280663061","name":"Get Evaluation Average","description":"","method":"GET","body":{},"parameters":[],"headers":[],"authentication":{"type":"bearer","token":"{% response 'body', 'req_96b7e6a46bd249dc8ed8be708b9c5501', 'b64::JC50b2tlbg==::46b', 'never', 60 %}"},"metaSortKey":-1660956656573,"isPrivate":false,"settingStoreCookies":true,"settingSendCookies":true,"settingDisableRenderRequestBody":false,"settingEncodeUrl":true,"settingRebuildPath":true,"settingFollowRedirects":"global","_type":"request"},{"_id":"req_12237e5b32c045b08710842a11905145","parentId":"fld_e2a5fb58c8644010b6b1d81383473705","modified":1689213922725,"created":1660956156403,"url":"https://localhost:3000/v1/hairdresser/professional-appointments","name":"Get Appointments Professional","description":"","method":"GET","body":{},"parameters":[],"headers":[],"authentication":{"type":"bearer","token":"{% response 'body', 'req_96b7e6a46bd249dc8ed8be708b9c5501', 'b64::JC50b2tlbg==::46b', 'never', 60 %}"},"metaSortKey":-1660956156403,"isPrivate":false,"settingStoreCookies":true,"settingSendCookies":true,"settingDisableRenderRequestBody":false,"settingEncodeUrl":true,"settingRebuildPath":true,"settingFollowRedirects":"global","_type":"request"},{"_id":"req_b809ea8507fc451382b66c9e21f90240","parentId":"fld_e2a5fb58c8644010b6b1d81383473705","modified":1660961038415,"created":1659579393203,"url":"https://localhost:3000/v1/hairdresser","name":"Create Hairdresser","description":"","method":"POST","body":{"mimeType":"application/json","text":"{\n\t\"name\": \"Alex\",\n\t\"Document\": \"15\",\n\t\"email\": \"alexcachopa@hotmail\",\n\t\"phone\": \"21979522952\",\n\t\"username\": \"alex\",\n\t\"password\": \"123456\",\n\t\"SaloonCode\": \"045B79\"\n}"},"parameters":[],"headers":[{"name":"Content-Type","value":"application/json","id":"pair_2b541d7bc70041d7bcfdafc11d074892"}],"authentication":{"type":"bearer","token":""},"metaSortKey":-1659924555257,"isPrivate":false,"settingStoreCookies":true,"settingSendCookies":true,"settingDisableRenderRequestBody":false,"settingEncodeUrl":true,"settingRebuildPath":true,"settingFollowRedirects":"global","_type":"request"},{"_id":"req_0ec6d406ffe246f1a85fe231ee9552ec","parentId":"fld_e2a5fb58c8644010b6b1d81383473705","modified":1697344162756,"created":1659733095960,"url":"https://localhost:3000/v1/hairdresser/send-work-availability","name":"Send Work Availability","description":"","method":"POST","body":{"mimeType":"application/json","text":"{\n  \"starthour\": \"2022-08-19T08:00:00\",\n  \"endhour\": \"2022-08-19T17:00:00\"\n}"},"parameters":[],"headers":[{"name":"Content-Type","value":"application/json","id":"pair_feb6e1c65da043fb81927dc2c74f9066"}],"authentication":{"type":"bearer","token":"{% response 'body', 'req_96b7e6a46bd249dc8ed8be708b9c5501', 'b64::JC50b2tlbg==::46b', 'never', 60 %}"},"metaSortKey":-1659924555207,"isPrivate":false,"settingStoreCookies":true,"settingSendCookies":true,"settingDisableRenderRequestBody":false,"settingEncodeUrl":true,"settingRebuildPath":true,"settingFollowRedirects":"global","_type":"request"},{"_id":"req_aed60c76723140fca071cf6d0bd8ee95","parentId":"fld_e2a5fb58c8644010b6b1d81383473705","modified":1697344115287,"created":1659924624281,"url":"https://localhost:3000/v1/hairdresser/professional-availability/48280663061","name":"Get Professional Availability","description":"","method":"GET","body":{},"parameters":[],"headers":[],"authentication":{"type":"bearer","token":"{% response 'body', 'req_96b7e6a46bd249dc8ed8be708b9c5501', 'b64::JC50b2tlbg==::46b', 'never', 60 %}"},"metaSortKey":-1659924555157,"isPrivate":false,"settingStoreCookies":true,"settingSendCookies":true,"settingDisableRenderRequestBody":false,"settingEncodeUrl":true,"settingRebuildPath":true,"settingFollowRedirects":"global","_type":"request"},{"_id":"req_6038fd6d8f0243acb8e6f9f40f08cbbb","parentId":"fld_e2a5fb58c8644010b6b1d81383473705","modified":1697344103758,"created":1659924555107,"url":"https://localhost:3000/v1/hairdresser/hairdressers-list/045B79","name":"Get Hairdressers List","description":"","method":"GET","body":{},"parameters":[],"headers":[],"authentication":{"type":"bearer","token":"{% response 'body', 'req_96b7e6a46bd249dc8ed8be708b9c5501', 'b64::JC50b2tlbg==::46b', 'never', 60 %}"},"metaSortKey":-1659924555107,"isPrivate":false,"settingStoreCookies":true,"settingSendCookies":true,"settingDisableRenderRequestBody":false,"settingEncodeUrl":true,"settingRebuildPath":true,"settingFollowRedirects":"global","_type":"request"},{"_id":"req_a697e5f8a1ce42cf9bfebf0b185952f3","parentId":"fld_d850d364745e44a889686e0d779727e6","modified":1689213902250,"created":1657942062479,"url":"https://localhost:3000/v1/saloon/","name":"Saloons","description":"","method":"GET","body":{},"parameters":[],"headers":[{"id":"pair_6ac5b1a115204370836019e55abe2257","name":"","value":"","description":""}],"authentication":{"type":"bearer","token":"{% response 'body', 'req_96b7e6a46bd249dc8ed8be708b9c5501', 'b64::JC50b2tlbg==::46b', 'never', 60 %}","disabled":false},"metaSortKey":-1657942062479,"isPrivate":false,"settingStoreCookies":true,"settingSendCookies":true,"settingDisableRenderRequestBody":false,"settingEncodeUrl":true,"settingRebuildPath":true,"settingFollowRedirects":"global","_type":"request"},{"_id":"fld_d850d364745e44a889686e0d779727e6","parentId":"wrk_2c9df4d661dc424f8fb66d6f9cb4a7c1","modified":1659974609629,"created":1659974609629,"name":"Saloon","description":"","environment":{},"environmentPropertyOrder":null,"metaSortKey":-1659974609629,"_type":"request_group"},{"_id":"env_6a39075651b6447f8b56391e78029826","parentId":"wrk_2c9df4d661dc424f8fb66d6f9cb4a7c1","modified":1697508028710,"created":1657894146996,"name":"Base Environment","data":{"baseUrl":"https://localhost:3000"},"dataPropertyOrder":{"&":["baseUrl"]},"color":null,"isPrivate":false,"metaSortKey":1657894146996,"_type":"environment"},{"_id":"jar_8089a8eabaab4af99a3d8024507668bc","parentId":"wrk_2c9df4d661dc424f8fb66d6f9cb4a7c1","modified":1657894146999,"created":1657894146999,"name":"Default Jar","cookies":[],"_type":"cookie_jar"},{"_id":"env_ffcdd946e43c4653aba9ba71240065fe","parentId":"env_6a39075651b6447f8b56391e78029826","modified":1697508032260,"created":1697507298962,"name":"New Environment","data":{"baseUrl":"http://localhost:8000"},"dataPropertyOrder":{"&":["baseUrl"]},"color":null,"isPrivate":true,"metaSortKey":1697507298962,"_type":"environment"}]}